abook_parser/__init__.py
abook_parser/__main__.py
abook_parser/parser.py
abook_parser/py.typed
abook_parser-0.1.0.dist-info/LICENSE
abook_parser-0.1.0.dist-info/METADATA
abook_parser-0.1.0.dist-info/WHEEL
abook_parser-0.1.0.dist-info/entry_points.txt
abook_parser-0.1.0.dist-info/top_level.txt
abook_parser-0.1.0.dist-info/RECORD
