Metadata-Version: 2.1
Name: abook_parser
Version: 0.1.0
Summary: parser for the abook CLI
Home-page: https://github.com/purarue/abook_parser
License: MIT
Classifier: License :: OSI Approved :: MIT License
Classifier: Programming Language :: Python
Classifier: Programming Language :: Python :: 3
Classifier: Programming Language :: Python :: 3 :: Only
Classifier: Programming Language :: Python :: 3.12
Classifier: Programming Language :: Python :: 3.13
Requires-Python: >=3.12
License-File: LICENSE
Requires-Dist: click>=8.1.6
Requires-Dist: pyfzf-iter
Provides-Extra: testing
Requires-Dist: flake8; extra == "testing"
Requires-Dist: mypy; extra == "testing"
Requires-Dist: pytest; extra == "testing"
